MANIFEST.in
README.rst
setup.cfg
setup.py
docs/Makefile
docs/authors.rst
docs/conf.py
docs/history.rst
docs/index.rst
docs/make.bat
docs/options.rst
docs/_build/doctrees/authors.doctree
docs/_build/doctrees/environment.pickle
docs/_build/doctrees/history.doctree
docs/_build/doctrees/index.doctree
docs/_build/doctrees/options.doctree
docs/_build/html/.buildinfo
docs/_build/html/authors.html
docs/_build/html/history.html
docs/_build/html/index.html
docs/_build/html/objects.inv
docs/_build/html/options.html
docs/_build/html/search.html
docs/_build/html/searchindex.js
docs/_build/html/_sources/authors.rst.txt
docs/_build/html/_sources/history.rst.txt
docs/_build/html/_sources/index.rst.txt
docs/_build/html/_sources/options.rst.txt
docs/_build/html/_static/impress-demo.css
docs/_build/html/_static/impress.js
docs/_build/html/_static/pygments.css
src/AUTHORS.txt
src/HISTORY.txt
src/LISENCE.txt
src/README.txt
src/sphinxjp/__init__.py
src/sphinxjp.themes.impressjs.egg-info/PKG-INFO
src/sphinxjp.themes.impressjs.egg-info/SOURCES.txt
src/sphinxjp.themes.impressjs.egg-info/dependency_links.txt
src/sphinxjp.themes.impressjs.egg-info/entry_points.txt
src/sphinxjp.themes.impressjs.egg-info/namespace_packages.txt
src/sphinxjp.themes.impressjs.egg-info/not-zip-safe
src/sphinxjp.themes.impressjs.egg-info/requires.txt
src/sphinxjp.themes.impressjs.egg-info/top_level.txt
src/sphinxjp/themes/__init__.py
src/sphinxjp/themes/impressjs/__init__.py
src/sphinxjp/themes/impressjs/directives.py
src/sphinxjp/themes/impressjs/templates/impressjs/layout.html
src/sphinxjp/themes/impressjs/templates/impressjs/page.html
src/sphinxjp/themes/impressjs/templates/impressjs/search.html
src/sphinxjp/themes/impressjs/templates/impressjs/theme.conf
src/sphinxjp/themes/impressjs/templates/impressjs/static/impress-demo.css
src/sphinxjp/themes/impressjs/templates/impressjs/static/impress.js