Metadata-Version: 1.1
Name: sphinxjp.themes.impressjs
Version: 0.1.4
Summary: A sphinx theme for HTML presentation style.
Home-page: https://github.com/shkumagai/sphinxjp.themes.impressjs
Author: Shoji KUMAGAI
Author-email: take dot this dot 2 dot your dot grave at gmail dot com
License: MIT
Keywords: sphinx,reStructuredText,theme,presentation
Platform: UNKNOWN
Classifier: Development Status :: 4 - Beta
Classifier: License :: OSI Approved :: MIT License
Classifier: Programming Language :: Python
Classifier: Topic :: Software Development
Classifier: Topic :: Software Development :: Documentation
Classifier: Topic :: Text Processing :: Markup
